{
  "workout_date": "2025-11-09",
  "athlete_id": null,
  "title": "W1 T1",
  "warmup_objective": "Foundation & Control",
  "status": "completed",
  "sessions": [
    {
      "session_code": null,
      "blocks": [
        {
          "block_code": "WU",
          "block_label": "A",
          "block_title": "Warm Up",
          "prescription": {
            "target_sets": 1,
            "notes": "5 min cardio + 3 rounds quality movements"
          },
          "performed": {
            "actual_sets": 1
          },
          "items": [
            {
              "item_sequence": 1,
              "prescription": {
                "target_duration_min": 5,
                "target_stroke_rate": 23,
                "target_damper": 5.5
              },
              "performed": {
                "actual_duration_min": 5
              },
              "exercise_name": "Bike"
            },
            {
              "item_sequence": 2,
              "prescription": {
                "target_rounds": 3,
                "target_reps": 10
              },
              "performed": {
                "actual_rounds": 3,
                "actual_reps": 10
              },
              "exercise_name": "Pvc Thoracic Rotation"
            },
            {
              "item_sequence": 3,
              "prescription": {
                "target_rounds": 3,
                "target_reps": 8,
                "target_sets_per_side": 2,
                "notes": "8 forward / 8 backward"
              },
              "performed": {
                "actual_rounds": 3,
                "actual_reps": 8,
                "actual_sets_per_side": 2
              },
              "exercise_name": "Scapular Cars"
            },
            {
              "item_sequence": 4,
              "prescription": {
                "target_rounds": 3,
                "target_reps": 8,
                "target_sets_per_side": 1,
                "target_weight_kg": 4.5,
                "notes": "Light 4-5kg"
              },
              "performed": {
                "actual_rounds": 3,
                "actual_reps": 8,
                "actual_sets_per_side": 1,
                "actual_weight_kg": 4.5
              },
              "exercise_name": "Db Supine Serratus Punch"
            }
          ]
        },
        {
          "block_code": "ACT",
          "block_label": "B",
          "block_title": "Activations",
          "prescription": {
            "target_rest_sec": 30
          },
          "performed": {
            "actual_sets": 1
          },
          "items": [
            {
              "item_sequence": 1,
              "prescription": {
                "target_sets": 3,
                "target_duration_sec": 20,
                "target_sets_per_side": 1,
                "equipment": "wall",
                "notes": "90 degree angle"
              },
              "performed": {
                "actual_sets": 3,
                "actual_duration_sec": 20,
                "actual_sets_per_side": 1
              },
              "exercise_name": "Isometric External Rotation"
            },
            {
              "item_sequence": 2,
              "prescription": {
                "target_sets": 3,
                "target_reps": 10,
                "target_sets_per_side": 1
              },
              "performed": {
                "actual_sets": 3,
                "actual_reps": 10,
                "actual_sets_per_side": 1
              },
              "exercise_name": "Banded Scapular Pulldown"
            }
          ]
        },
        {
          "block_code": "STR",
          "block_label": "C",
          "block_title": "Landmine Press Half Kneeling",
          "prescription": {
            "target_sets": 3,
            "target_reps": 8,
            "target_sets_per_side": 1,
            "target_rpe": 5.75,
            "target_rest_min": 1.5,
            "target_tempo": "3-0-2-0",
            "notes": "3 sec down, 2 sec up"
          },
          "performed": {
            "actual_sets": 3,
            "actual_reps": 8,
            "actual_sets_per_side": 1,
            "actual_weight_kg": 20,
            "notes": "Right shoulder hurt 5/10 in set 1. Left rear shoulder pain on lowering. Bar only (20kg)."
          },
          "items": [
            {
              "item_sequence": 1,
              "prescription": {
                "target_sets": 3,
                "target_reps": 8,
                "target_sets_per_side": 1,
                "target_tempo": "3-0-2-0",
                "equipment": "barbell",
                "position": "half_kneeling"
              },
              "performed": {
                "actual_sets": 3,
                "actual_reps": 8,
                "actual_sets_per_side": 1,
                "actual_weight_kg": 20
              },
              "exercise_name": "Landmine Press"
            }
          ]
        },
        {
          "block_code": "STR",
          "block_label": "D",
          "block_title": "Dumbbell Romanian Deadlift",
          "prescription": {
            "target_sets": 3,
            "target_reps": 8,
            "target_rpe": 5.75,
            "target_rest_min": 1.5
          },
          "performed": {
            "actual_sets": 3,
            "actual_reps": 8,
            "actual_weight_kg": 10
          },
          "items": [
            {
              "item_sequence": 1,
              "prescription": {
                "target_sets": 3,
                "target_reps": 8
              },
              "performed": {
                "actual_sets": 3,
                "actual_reps": 8,
                "actual_weight_kg": 10
              },
              "exercise_name": "Dumbbell Rdl"
            }
          ]
        },
        {
          "block_code": "ACC",
          "block_label": "E",
          "block_title": "One arm chest supported row",
          "prescription": {
            "target_sets": 3,
            "target_reps": 10,
            "target_rpe": 6,
            "target_rest_min": 1.5
          },
          "performed": {
            "actual_sets": 3,
            "actual_reps": 10,
            "actual_weight_kg": 10
          },
          "items": [
            {
              "item_sequence": 1,
              "prescription": {
                "target_sets": 3,
                "target_reps": 10
              },
              "performed": {
                "actual_sets": 3,
                "actual_reps": 10,
                "actual_weight_kg": 10
              },
              "exercise_name": "One Arm Chest Supported Row"
            }
          ]
        },
        {
          "block_code": "ACC",
          "block_label": "F",
          "block_title": "Tall Kneeling Cable Pallof Press",
          "prescription": {
            "target_sets": 3,
            "target_reps": 10,
            "target_sets_per_side": 1,
            "target_rest_min": 1
          },
          "performed": {
            "actual_sets": 3,
            "actual_reps": 10,
            "actual_sets_per_side": 1,
            "actual_weight_kg": 7.5,
            "notes": "Strange movement"
          },
          "items": [
            {
              "item_sequence": 1,
              "prescription": {
                "target_sets": 3,
                "target_reps": 10,
                "target_sets_per_side": 1,
                "equipment": "cable",
                "position": "tall_kneeling"
              },
              "performed": {
                "actual_sets": 3,
                "actual_reps": 10,
                "actual_sets_per_side": 1,
                "actual_weight_kg": 7.5
              },
              "exercise_name": "Pallof Press"
            }
          ]
        },
        {
          "block_code": "ACC",
          "block_label": "G",
          "block_title": "DB Suitcase Carry",
          "prescription": {
            "target_sets": 3,
            "target_distance_m": 20,
            "target_sets_per_side": 1,
            "target_rest_min": 1,
            "notes": "Start with left hand"
          },
          "performed": {
            "actual_sets": 3,
            "actual_distance_m": 20,
            "actual_sets_per_side": 1,
            "notes": "Started at 12kg, progressed to 18kg in last set"
          },
          "items": [
            {
              "item_sequence": 1,
              "prescription": {
                "target_sets": 3,
                "target_distance_m": 20,
                "target_sets_per_side": 1,
                "equipment": "dumbbell"
              },
              "performed": {
                "actual_sets": 3,
                "actual_distance_m": 20,
                "actual_sets_per_side": 1,
                "actual_weight_kg": [
                  12,
                  12,
                  18
                ]
              },
              "exercise_name": "Suitcase Carry"
            }
          ]
        },
        {
          "block_code": "ACC",
          "block_label": "H",
          "block_title": "Prone Low Trap Raise",
          "prescription": {
            "target_sets": 2,
            "target_reps": 12,
            "target_rest_min": 1,
            "notes": "Find space between shoulder blades that doesn't create pain"
          },
          "performed": {
            "actual_sets": 2,
            "actual_reps": 12,
            "notes": "Caught beneath left scapula during first set"
          },
          "items": [
            {
              "item_sequence": 1,
              "prescription": {
                "target_sets": 2,
                "target_reps": 12
              },
              "performed": {
                "actual_sets": 2,
                "actual_reps": 12
              },
              "exercise_name": "Prone Low Trap Raise"
            }
          ]
        },
        {
          "block_code": "CD",
          "block_label": "I",
          "block_title": "Bike / Row",
          "prescription": {
            "target_duration_min": 10
          },
          "performed": {
            "actual_duration_min": 10
          },
          "items": [
            {
              "item_sequence": 1,
              "prescription": {
                "target_duration_min": 10
              },
              "performed": {
                "actual_duration_min": 10
              },
              "exercise_name": "Bike"
            }
          ]
        }
      ]
    }
  ]
}